[
  {
    "joints": [
      {
        "x": 0.5,
        "y": 0.2
      },
      {
        "x": 0.47,
        "y": 0.18
      },
      {
        "x": 0.53,
        "y": 0.18
      },
      {
        "x": 0.44,
        "y": 0.19
      },
      {
        "x": 0.56,
        "y": 0.19
      },
      {
        "x": 0.42,
        "y": 0.32
      },
      {
        "x": 0.58,
        "y": 0.32
      },
      {
        "x": 0.38,
        "y": 0.45
      },
      {
        "x": 0.62,
        "y": 0.45
      },
      {
        "x": 0.36,
        "y": 0.56
      },
      {
        "x": 0.64,
        "y": 0.56
      },
      {
        "x": 0.44,
        "y": 0.62
      },
      {
        "x": 0.56,
        "y": 0.62
      },
      null,
      null,
      null,
      null
    ],
    "easing": "ease-in-out"
  },
  {
    "joints": [
      {
        "x": 0.52,
        "y": 0.2
      },
      {
        "x": 0.49,
        "y": 0.18
      },
      {
        "x": 0.55,
        "y": 0.18
      },
      {
        "x": 0.46,
        "y": 0.19
      },
      {
        "x": 0.58,
        "y": 0.19
      },
      {
        "x": 0.42,
        "y": 0.32
      },
      {
        "x": 0.6,
        "y": 0.32
      },
      {
        "x": 0.36,
        "y": 0.42
      },
      {
        "x": 0.65,
        "y": 0.4
      },
      {
        "x": 0.32,
        "y": 0.32
      },
      {
        "x": 0.7,
        "y": 0.32
      },
      {
        "x": 0.44,
        "y": 0.62
      },
      {
        "x": 0.57,
        "y": 0.62
      },
      null,
      null,
      null,
      null
    ],
    "easing": "ease-in-out"
  },
  {
    "joints": [
      {
        "x": 0.5,
        "y": 0.2
      },
      {
        "x": 0.47,
        "y": 0.18
      },
      {
        "x": 0.53,
        "y": 0.18
      },
      {
        "x": 0.44,
        "y": 0.19
      },
      {
        "x": 0.56,
        "y": 0.19
      },
      {
        "x": 0.42,
        "y": 0.32
      },
      {
        "x": 0.58,
        "y": 0.32
      },
      {
        "x": 0.38,
        "y": 0.45
      },
      {
        "x": 0.62,
        "y": 0.45
      },
      {
        "x": 0.36,
        "y": 0.56
      },
      {
        "x": 0.64,
        "y": 0.56
      },
      {
        "x": 0.44,
        "y": 0.62
      },
      {
        "x": 0.56,
        "y": 0.62
      },
      null,
      null,
      null,
      null
    ],
    "easing": "ease-in-out"
  }
]